<?xml version="1.0" encoding="utf-8"?>
<ArrayOfDependency>
  <Dependency>
    <Id>196</Id>
    <CurrentTaskId>2</CurrentTaskId>
    <LastTaskId>1</LastTaskId>
  </Dependency>
  <Dependency>
    <Id>197</Id>
    <CurrentTaskId>3</CurrentTaskId>
    <LastTaskId>2</LastTaskId>
  </Dependency>
  <Dependency>
    <Id>198</Id>
    <CurrentTaskId>4</CurrentTaskId>
    <LastTaskId>3</LastTaskId>
  </Dependency>
  <Dependency>
    <Id>199</Id>
    <CurrentTaskId>5</CurrentTaskId>
    <LastTaskId>4</LastTaskId>
  </Dependency>
  <Dependency>
    <Id>200</Id>
    <CurrentTaskId>6</CurrentTaskId>
    <LastTaskId>5</LastTaskId>
  </Dependency>
  <Dependency>
    <Id>201</Id>
    <CurrentTaskId>7</CurrentTaskId>
    <LastTaskId>6</LastTaskId>
  </Dependency>
  <Dependency>
    <Id>202</Id>
    <CurrentTaskId>8</CurrentTaskId>
    <LastTaskId>7</LastTaskId>
  </Dependency>
  <Dependency>
    <Id>203</Id>
    <CurrentTaskId>9</CurrentTaskId>
    <LastTaskId>8</LastTaskId>
  </Dependency>
  <Dependency>
    <Id>204</Id>
    <CurrentTaskId>10</CurrentTaskId>
    <LastTaskId>9</LastTaskId>
  </Dependency>
  <Dependency>
    <Id>205</Id>
    <CurrentTaskId>11</CurrentTaskId>
    <LastTaskId>10</LastTaskId>
  </Dependency>
  <Dependency>
    <Id>206</Id>
    <CurrentTaskId>12</CurrentTaskId>
    <LastTaskId>11</LastTaskId>
  </Dependency>
  <Dependency>
    <Id>207</Id>
    <CurrentTaskId>13</CurrentTaskId>
    <LastTaskId>12</LastTaskId>
  </Dependency>
  <Dependency>
    <Id>208</Id>
    <CurrentTaskId>14</CurrentTaskId>
    <LastTaskId>13</LastTaskId>
  </Dependency>
  <Dependency>
    <Id>209</Id>
    <CurrentTaskId>15</CurrentTaskId>
    <LastTaskId>14</LastTaskId>
  </Dependency>
  <Dependency>
    <Id>210</Id>
    <CurrentTaskId>16</CurrentTaskId>
    <LastTaskId>15</LastTaskId>
  </Dependency>
  <Dependency>
    <Id>211</Id>
    <CurrentTaskId>17</CurrentTaskId>
    <LastTaskId>16</LastTaskId>
  </Dependency>
  <Dependency>
    <Id>212</Id>
    <CurrentTaskId>18</CurrentTaskId>
    <LastTaskId>17</LastTaskId>
  </Dependency>
  <Dependency>
    <Id>213</Id>
    <CurrentTaskId>19</CurrentTaskId>
    <LastTaskId>18</LastTaskId>
  </Dependency>
  <Dependency>
    <Id>214</Id>
    <CurrentTaskId>20</CurrentTaskId>
    <LastTaskId>19</LastTaskId>
  </Dependency>
  <Dependency>
    <Id>215</Id>
    <CurrentTaskId>21</CurrentTaskId>
    <LastTaskId>20</LastTaskId>
  </Dependency>
  <Dependency>
    <Id>216</Id>
    <CurrentTaskId>22</CurrentTaskId>
    <LastTaskId>21</LastTaskId>
  </Dependency>
  <Dependency>
    <Id>217</Id>
    <CurrentTaskId>23</CurrentTaskId>
    <LastTaskId>22</LastTaskId>
  </Dependency>
  <Dependency>
    <Id>218</Id>
    <CurrentTaskId>24</CurrentTaskId>
    <LastTaskId>23</LastTaskId>
  </Dependency>
  <Dependency>
    <Id>219</Id>
    <CurrentTaskId>25</CurrentTaskId>
    <LastTaskId>24</LastTaskId>
  </Dependency>
  <Dependency>
    <Id>220</Id>
    <CurrentTaskId>26</CurrentTaskId>
    <LastTaskId>25</LastTaskId>
  </Dependency>
  <Dependency>
    <Id>221</Id>
    <CurrentTaskId>27</CurrentTaskId>
    <LastTaskId>26</LastTaskId>
  </Dependency>
  <Dependency>
    <Id>222</Id>
    <CurrentTaskId>28</CurrentTaskId>
    <LastTaskId>27</LastTaskId>
  </Dependency>
  <Dependency>
    <Id>223</Id>
    <CurrentTaskId>29</CurrentTaskId>
    <LastTaskId>28</LastTaskId>
  </Dependency>
  <Dependency>
    <Id>224</Id>
    <CurrentTaskId>30</CurrentTaskId>
    <LastTaskId>29</LastTaskId>
  </Dependency>
  <Dependency>
    <Id>225</Id>
    <CurrentTaskId>31</CurrentTaskId>
    <LastTaskId>30</LastTaskId>
  </Dependency>
  <Dependency>
    <Id>226</Id>
    <CurrentTaskId>32</CurrentTaskId>
    <LastTaskId>31</LastTaskId>
  </Dependency>
  <Dependency>
    <Id>227</Id>
    <CurrentTaskId>33</CurrentTaskId>
    <LastTaskId>32</LastTaskId>
  </Dependency>
  <Dependency>
    <Id>228</Id>
    <CurrentTaskId>34</CurrentTaskId>
    <LastTaskId>33</LastTaskId>
  </Dependency>
  <Dependency>
    <Id>229</Id>
    <CurrentTaskId>35</CurrentTaskId>
    <LastTaskId>34</LastTaskId>
  </Dependency>
  <Dependency>
    <Id>230</Id>
    <CurrentTaskId>36</CurrentTaskId>
    <LastTaskId>35</LastTaskId>
  </Dependency>
  <Dependency>
    <Id>231</Id>
    <CurrentTaskId>37</CurrentTaskId>
    <LastTaskId>36</LastTaskId>
  </Dependency>
  <Dependency>
    <Id>232</Id>
    <CurrentTaskId>38</CurrentTaskId>
    <LastTaskId>37</LastTaskId>
  </Dependency>
  <Dependency>
    <Id>233</Id>
    <CurrentTaskId>39</CurrentTaskId>
    <LastTaskId>38</LastTaskId>
  </Dependency>
  <Dependency>
    <Id>234</Id>
    <CurrentTaskId>40</CurrentTaskId>
    <LastTaskId>39</LastTaskId>
  </Dependency>
</ArrayOfDependency>